{
  "lastUpdated": "2026-06-28T12:15:17.420Z",
  "reportPeriod": {
    "days": 90,
    "startDate": "2026-03-30",
    "endDate": "2026-06-28",
    "startISO": "2026-03-30T12:14:58.808Z",
    "endISO": "2026-06-28T12:14:58.808Z",
    "label": "Mar 30, 2026 ? Jun 28, 2026"
  },
  "college": "College of Arts & Sciences",
  "domain": "artsci.tamu.edu",
  "ga4": {
    "sessions": {
      "value": "652.7k",
      "raw": 652716
    },
    "newUsers": {
      "value": "457.5k",
      "raw": 457454
    },
    "engagementRate": {
      "value": "36%",
      "raw": 36
    },
    "avgDuration": {
      "value": "2:59",
      "raw": 179
    },
    "pageViews": {
      "value": "1057.8k",
      "raw": 1057840
    },
    "bounceRate": {
      "value": "64%",
      "raw": 64
    },
    "admissionsVisits": {
      "value": "4.1k",
      "raw": 4113
    },
    "topPages": [
      {
        "path": "/",
        "views": 26766
      },
      {
        "path": "/economics/index.html",
        "views": 16612
      },
      {
        "path": "/geosonline/index.html",
        "views": 15374
      },
      {
        "path": "/mathematics/index.html",
        "views": 11183
      },
      {
        "path": "/english/index.html",
        "views": 11111
      }
    ],
    "monthlyTrend": {
      "buckets": [
        {
          "sessions": 121705,
          "newUsers": 65923,
          "bounceRate": 56
        },
        {
          "sessions": 114416,
          "newUsers": 67631,
          "bounceRate": 57
        },
        {
          "sessions": 116244,
          "newUsers": 80872,
          "bounceRate": 63
        },
        {
          "sessions": 102193,
          "newUsers": 73294,
          "bounceRate": 65
        },
        {
          "sessions": 99237,
          "newUsers": 72860,
          "bounceRate": 68
        },
        {
          "sessions": 110523,
          "newUsers": 90937,
          "bounceRate": 74
        }
      ],
      "labels": [
        "Apr",
        "Apr",
        "May",
        "May",
        "Jun",
        "Jun"
      ]
    },
    "deptBreakdown": [
      {
        "name": "Mathematics",
        "path": "/mathematics/",
        "sessions": 71543,
        "newUsers": 26762,
        "avgDuration": 130,
        "bounceRate": 33
      },
      {
        "name": "Chemistry",
        "path": "/chemistry/",
        "sessions": 58225,
        "newUsers": 24530,
        "avgDuration": 153,
        "bounceRate": 33
      },
      {
        "name": "Biology",
        "path": "/biology/",
        "sessions": 50327,
        "newUsers": 15280,
        "avgDuration": 165,
        "bounceRate": 29
      },
      {
        "name": "Psychological & Brain Sciences",
        "path": "/psychological-brain-sciences/",
        "sessions": 45627,
        "newUsers": 15006,
        "avgDuration": 282,
        "bounceRate": 27
      },
      {
        "name": "Economics",
        "path": "/economics/",
        "sessions": 34557,
        "newUsers": 19861,
        "avgDuration": 183,
        "bounceRate": 26
      },
      {
        "name": "Statistics",
        "path": "/statistics/",
        "sessions": 18016,
        "newUsers": 7090,
        "avgDuration": 202,
        "bounceRate": 25
      },
      {
        "name": "Physics & Astronomy",
        "path": "/physics-astronomy/",
        "sessions": 17119,
        "newUsers": 8138,
        "avgDuration": 195,
        "bounceRate": 32
      },
      {
        "name": "English",
        "path": "/english/",
        "sessions": 16862,
        "newUsers": 11317,
        "avgDuration": 116,
        "bounceRate": 31
      },
      {
        "name": "Geology & Geophysics",
        "path": "/geology-geophysics/",
        "sessions": 16411,
        "newUsers": 10776,
        "avgDuration": 136,
        "bounceRate": 41
      },
      {
        "name": "Communication & Journalism",
        "path": "/comm-journalism/",
        "sessions": 13802,
        "newUsers": 5341,
        "avgDuration": 112,
        "bounceRate": 28
      },
      {
        "name": "Geography",
        "path": "/geography/",
        "sessions": 12383,
        "newUsers": 7454,
        "avgDuration": 167,
        "bounceRate": 35
      },
      {
        "name": "Atmospheric Sciences",
        "path": "/atmos-science/",
        "sessions": 11822,
        "newUsers": 6954,
        "avgDuration": 181,
        "bounceRate": 35
      },
      {
        "name": "Global Languages & Cultures",
        "path": "/global-lang-cultures/",
        "sessions": 9944,
        "newUsers": 3958,
        "avgDuration": 236,
        "bounceRate": 25
      },
      {
        "name": "Philosophy",
        "path": "/philosophy/",
        "sessions": 9852,
        "newUsers": 5277,
        "avgDuration": 119,
        "bounceRate": 34
      },
      {
        "name": "History",
        "path": "/history/",
        "sessions": 9005,
        "newUsers": 4472,
        "avgDuration": 174,
        "bounceRate": 27
      },
      {
        "name": "Sociology",
        "path": "/sociology/",
        "sessions": 8647,
        "newUsers": 4738,
        "avgDuration": 149,
        "bounceRate": 36
      },
      {
        "name": "Oceanography",
        "path": "/oceanography/",
        "sessions": 8534,
        "newUsers": 5795,
        "avgDuration": 124,
        "bounceRate": 40
      },
      {
        "name": "Anthropology",
        "path": "/anthropology/",
        "sessions": 8060,
        "newUsers": 6027,
        "avgDuration": 123,
        "bounceRate": 41
      }
    ],
    "deptTrend": {
      "labels": [
        "Apr",
        "May",
        "Jun"
      ],
      "departments": {
        "Anthropology": [
          1889,
          1474,
          4398
        ],
        "Atmospheric Sciences": [
          4806,
          3557,
          3364
        ],
        "Biology": [
          20461,
          16993,
          12277
        ],
        "Chemistry": [
          19726,
          15567,
          22558
        ],
        "Communication & Journalism": [
          6091,
          4811,
          3503
        ],
        "Economics": [
          9956,
          7006,
          17200
        ],
        "English": [
          7290,
          2314,
          7203
        ],
        "Geography": [
          5098,
          3509,
          4366
        ],
        "Geology & Geophysics": [
          7128,
          3980,
          5467
        ],
        "Global Languages & Cultures": [
          4107,
          2876,
          2819
        ],
        "History": [
          3871,
          2579,
          2219
        ],
        "Mathematics": [
          29732,
          24222,
          16852
        ],
        "Oceanography": [
          3546,
          2135,
          2468
        ],
        "Philosophy": [
          4941,
          2475,
          2288
        ],
        "Physics & Astronomy": [
          7371,
          5003,
          4574
        ],
        "Psychological & Brain Sciences": [
          18809,
          15063,
          10609
        ],
        "Sociology": [
          4551,
          1849,
          2508
        ],
        "Statistics": [
          7195,
          5388,
          5000
        ]
      }
    }
  },
  "siteimprove": {
    "scope": "artsci.tamu.edu (Cascade sites)",
    "accessibilityScore": {
      "value": "83",
      "raw": 83
    },
    "accessibilityAA": {
      "value": "83",
      "raw": 83
    },
    "accessibilityTotal": {
      "value": "89",
      "raw": 89
    },
    "seoScore": {
      "value": "82",
      "raw": 82
    },
    "mobileScore": {
      "value": "55",
      "raw": 55
    },
    "qaScore": {
      "value": "60",
      "raw": 60
    },
    "dciTotal": {
      "value": "77",
      "raw": 77
    },
    "brokenLinks": {
      "value": "1746",
      "raw": 1746
    },
    "qualityIssues": {
      "value": "138",
      "raw": 138
    }
  },
  "freshdesk": {
    "ticketVolume": {
      "value": "274",
      "raw": 274
    },
    "resolutionRate": {
      "value": "83%",
      "raw": 83
    },
    "avgResponseTime": {
      "value": "6.9h",
      "raw": "6.9"
    },
    "csatScore": {
      "value": "N/A",
      "raw": "N/A"
    },
    "deptBreakdown": [
      {
        "name": "Other / Unclassified",
        "count": 156
      },
      {
        "name": "History",
        "count": 45
      },
      {
        "name": "Geography",
        "count": 15
      },
      {
        "name": "Geology & Geophysics",
        "count": 13
      },
      {
        "name": "Communication & Journalism",
        "count": 8
      },
      {
        "name": "English",
        "count": 7
      },
      {
        "name": "Chemistry",
        "count": 7
      },
      {
        "name": "Atmospheric Sciences",
        "count": 6
      },
      {
        "name": "Biology",
        "count": 5
      },
      {
        "name": "Oceanography",
        "count": 3
      }
    ],
    "ticketTrend": [
      {
        "label": "Apr 12",
        "count": 12
      },
      {
        "label": "Apr 19",
        "count": 23
      },
      {
        "label": "Apr 26",
        "count": 27
      },
      {
        "label": "May 3",
        "count": 18
      },
      {
        "label": "May 10",
        "count": 20
      },
      {
        "label": "May 17",
        "count": 44
      },
      {
        "label": "May 24",
        "count": 20
      },
      {
        "label": "May 31",
        "count": 8
      },
      {
        "label": "Jun 7",
        "count": 22
      },
      {
        "label": "Jun 14",
        "count": 16
      },
      {
        "label": "Jun 21",
        "count": 7
      },
      {
        "label": "Jun 28",
        "count": 18
      }
    ]
  },
  "clarity": {
    "status": "active",
    "hasData": true,
    "dataWindow": "Last 3 days (API limit)",
    "totalSessions": {
      "value": "19.0k",
      "raw": 19040
    },
    "uniqueUsers": {
      "value": "?",
      "raw": 0
    },
    "scrollDepth": {
      "value": "?",
      "raw": 0
    },
    "deadClicks": {
      "value": "3.1k",
      "raw": 3080
    },
    "deadClickRate": {
      "value": "16%",
      "raw": 16
    },
    "rageClicks": {
      "value": "?",
      "raw": 0
    },
    "recordings": {
      "value": "?",
      "raw": 0
    },
    "pageViews": {
      "value": "1.1k",
      "raw": 1089
    },
    "topPages": [],
    "rawData": [
      {
        "sessionsCount": "9",
        "sessionsWithMetricPercentage": 11.11,
        "sessionsWithoutMetricPercentage": 88.89,
        "pagesViews": "1",
        "subTotal": "1",
        "Browser": "Other",
        "Device": "Mobile"
      },
      {
        "sessionsCount": "2",
        "sessionsWithMetricPercentage": 50,
        "sessionsWithoutMetricPercentage": 50,
        "pagesViews": "1",
        "subTotal": "1",
        "Browser": "Chrome",
        "Device": "Mobile"
      },
      {
        "sessionsCount": "737",
        "sessionsWithMetricPercentage": 6.51,
        "sessionsWithoutMetricPercentage": 93.49,
        "pagesViews": "61",
        "subTotal": "113",
        "Browser": "ChromeMobile",
        "Device": "Mobile"
      }
    ]
  },
  "centersInventory": [
    {
      "name": "Race and Ethnic Studies Institute",
      "url": "https://liberalarts.tamu.edu/resi/",
      "platform": "WordPress",
      "monitored": false
    },
    {
      "name": "Glasscock Center for Humanities Research",
      "url": "https://liberalarts.tamu.edu/glasscock/",
      "platform": "WordPress",
      "monitored": false
    },
    {
      "name": "Center of Digital Humanities Research",
      "url": "https://liberalarts.tamu.edu/codhr/",
      "platform": "WordPress",
      "monitored": true
    },
    {
      "name": "Center for the Study of First Americans",
      "url": "https://liberalarts.tamu.edu/csfa/",
      "platform": "WordPress",
      "monitored": true
    },
    {
      "name": "Texas Research Data Center",
      "url": "https://liberalarts.tamu.edu/txrdc/",
      "platform": "WordPress",
      "monitored": false
    },
    {
      "name": "Berg-Hughes Center",
      "url": "https://berg-hughes.tamu.edu/",
      "platform": "Cascade",
      "monitored": true
    },
    {
      "name": "Ctr for Approximation & Mathematical Data",
      "url": "https://sites.google.com/tamu.edu/camda/",
      "platform": "Google Sites",
      "monitored": true
    },
    {
      "name": "Ctr for Atmospheric Chemistry & Environment",
      "url": "https://cace.tamu.edu/",
      "platform": "Cascade",
      "monitored": true
    },
    {
      "name": "Center for Biological Clocks Research",
      "url": "https://clocks.tamu.edu/",
      "platform": "WordPress",
      "monitored": false
    },
    {
      "name": "Ctr for Chemical Characterization & Analysis",
      "url": "https://sites.google.com/view/elemental-analysis-laboratory/",
      "platform": "Google Sites",
      "monitored": true
    },
    {
      "name": "Ctr for Electrochemical Systems & H Research",
      "url": "http://www.txpec.net/",
      "platform": "Unknown",
      "monitored": true
    },
    {
      "name": "Ctr for Maritime Archaeology & Conservation",
      "url": "https://nautarch.tamu.edu/",
      "platform": "WordPress",
      "monitored": false
    },
    {
      "name": "Ctr for Mathematics and Science Education",
      "url": "https://cmse.tamu.edu/",
      "platform": "WordPress",
      "monitored": false
    },
    {
      "name": "Center for Statistical Bioinformatics",
      "url": "https://statbio.stat.tamu.edu/",
      "platform": "WordPress",
      "monitored": true
    },
    {
      "name": "Ctr for Surface Science & Mechanochemistry",
      "url": "https://www.chem.tamu.edu/cmcc/",
      "platform": "HTML/CSS",
      "monitored": false
    },
    {
      "name": "Center for Tectonophysics",
      "url": "https://tectono.tamu.edu/",
      "platform": "Cascade",
      "monitored": true
    },
    {
      "name": "Center for Theoretical Physics",
      "url": "https://iqse.tamu.edu/ctp/",
      "platform": "WordPress",
      "monitored": false
    },
    {
      "name": "Cyclotron Institute",
      "url": "https://cyclotron.tamu.edu/",
      "platform": "WordPress",
      "monitored": false
    },
    {
      "name": "Geochemical & Environmental Research Group",
      "url": "https://gerg.tamu.edu/",
      "platform": "Cascade",
      "monitored": true
    },
    {
      "name": "Mitchell Institute for Physics & Astronomy",
      "url": "https://mitchell.tamu.edu/",
      "platform": "WordPress",
      "monitored": false
    },
    {
      "name": "Inst. for Applied Math & Computational Science",
      "url": "https://iamcs.tamu.edu/",
      "platform": "WordPress",
      "monitored": false
    },
    {
      "name": "Institute for Scientific Computation",
      "url": "https://isc.tamu.edu/",
      "platform": "HTML/CSS",
      "monitored": false
    },
    {
      "name": "Institute for Quantum Science and Engineering",
      "url": "https://iqse.tamu.edu/",
      "platform": "WordPress",
      "monitored": false
    },
    {
      "name": "Institute of Nautical Archaeology",
      "url": "https://nauticalarch.org/",
      "platform": "WordPress",
      "monitored": false
    },
    {
      "name": "Laboratory for Synthetic Biologic Interactions",
      "url": "https://lsbi.chem.tamu.edu/",
      "platform": "HTML/CSS",
      "monitored": false
    },
    {
      "name": "Nuclear Solutions Institute",
      "url": "https://nsi.tamu.edu/",
      "platform": "WordPress",
      "monitored": false
    },
    {
      "name": "Office of the Texas State Climatologist",
      "url": "https://climatexas.tamu.edu/",
      "platform": "Cascade",
      "monitored": true
    },
    {
      "name": "Public Policy Research Institute",
      "url": "https://ppri.tamu.edu/",
      "platform": "WordPress",
      "monitored": false
    },
    {
      "name": "Southern Regional Climate Center",
      "url": "https://www.srcc.tamu.edu/",
      "platform": "HTML/CSS",
      "monitored": false
    },
    {
      "name": "Texas Center for Extreme Weather",
      "url": "https://texasclimate.tamu.edu/",
      "platform": "Cascade",
      "monitored": true
    }
  ]
}