{
  "lastUpdated": "2026-06-14T12:15:08.540Z",
  "reportPeriod": {
    "days": 180,
    "startDate": "2025-12-16",
    "endDate": "2026-06-14",
    "startISO": "2025-12-16T13:14:57.118Z",
    "endISO": "2026-06-14T12:14:57.118Z",
    "label": "Dec 16, 2025 ? Jun 14, 2026"
  },
  "college": "College of Arts & Sciences",
  "domain": "artsci.tamu.edu",
  "ga4": {
    "sessions": {
      "value": "1474.6k",
      "raw": 1474563
    },
    "newUsers": {
      "value": "962.4k",
      "raw": 962362
    },
    "engagementRate": {
      "value": "36%",
      "raw": 36
    },
    "avgDuration": {
      "value": "2:55",
      "raw": 175
    },
    "pageViews": {
      "value": "2321.7k",
      "raw": 2321651
    },
    "bounceRate": {
      "value": "64%",
      "raw": 64
    },
    "admissionsVisits": {
      "value": "14.2k",
      "raw": 14193
    },
    "topPages": [
      {
        "path": "/",
        "views": 54546
      },
      {
        "path": "/atmos-science/index.html",
        "views": 46929
      },
      {
        "path": "/geology-geophysics/index.html",
        "views": 34629
      },
      {
        "path": "/english/index.html",
        "views": 27016
      },
      {
        "path": "/biology/index.html",
        "views": 23799
      }
    ],
    "monthlyTrend": {
      "buckets": [
        {
          "sessions": 184831,
          "newUsers": 114171,
          "bounceRate": 53
        },
        {
          "sessions": 260607,
          "newUsers": 156232,
          "bounceRate": 62
        },
        {
          "sessions": 319882,
          "newUsers": 234338,
          "bounceRate": 72
        },
        {
          "sessions": 272041,
          "newUsers": 162079,
          "bounceRate": 59
        },
        {
          "sessions": 221954,
          "newUsers": 146272,
          "bounceRate": 59
        },
        {
          "sessions": 196048,
          "newUsers": 142114,
          "bounceRate": 67
        }
      ],
      "labels": [
        "Jan",
        "Feb",
        "Mar",
        "Apr",
        "May",
        "Jun"
      ]
    },
    "deptBreakdown": [
      {
        "name": "Mathematics",
        "path": "/mathematics/",
        "sessions": 155702,
        "newUsers": 47841,
        "avgDuration": 140,
        "bounceRate": 31
      },
      {
        "name": "Chemistry",
        "path": "/chemistry/",
        "sessions": 111776,
        "newUsers": 40874,
        "avgDuration": 151,
        "bounceRate": 31
      },
      {
        "name": "Biology",
        "path": "/biology/",
        "sessions": 110557,
        "newUsers": 35025,
        "avgDuration": 188,
        "bounceRate": 26
      },
      {
        "name": "Psychological & Brain Sciences",
        "path": "/psychological-brain-sciences/",
        "sessions": 104371,
        "newUsers": 33873,
        "avgDuration": 213,
        "bounceRate": 27
      },
      {
        "name": "Economics",
        "path": "/economics/",
        "sessions": 57613,
        "newUsers": 18628,
        "avgDuration": 152,
        "bounceRate": 25
      },
      {
        "name": "Atmospheric Sciences",
        "path": "/atmos-science/",
        "sessions": 56956,
        "newUsers": 47037,
        "avgDuration": 248,
        "bounceRate": 40
      },
      {
        "name": "Geology & Geophysics",
        "path": "/geology-geophysics/",
        "sessions": 47357,
        "newUsers": 35974,
        "avgDuration": 130,
        "bounceRate": 39
      },
      {
        "name": "Statistics",
        "path": "/statistics/",
        "sessions": 45628,
        "newUsers": 15193,
        "avgDuration": 172,
        "bounceRate": 24
      },
      {
        "name": "English",
        "path": "/english/",
        "sessions": 41219,
        "newUsers": 27296,
        "avgDuration": 142,
        "bounceRate": 30
      },
      {
        "name": "Physics & Astronomy",
        "path": "/physics-astronomy/",
        "sessions": 40059,
        "newUsers": 16334,
        "avgDuration": 167,
        "bounceRate": 31
      },
      {
        "name": "Geography",
        "path": "/geography/",
        "sessions": 35905,
        "newUsers": 22714,
        "avgDuration": 151,
        "bounceRate": 29
      },
      {
        "name": "Global Languages & Cultures",
        "path": "/global-lang-cultures/",
        "sessions": 33830,
        "newUsers": 21668,
        "avgDuration": 181,
        "bounceRate": 27
      },
      {
        "name": "Philosophy",
        "path": "/philosophy/",
        "sessions": 32773,
        "newUsers": 18659,
        "avgDuration": 125,
        "bounceRate": 32
      },
      {
        "name": "Communication & Journalism",
        "path": "/comm-journalism/",
        "sessions": 31197,
        "newUsers": 10085,
        "avgDuration": 120,
        "bounceRate": 26
      },
      {
        "name": "Sociology",
        "path": "/sociology/",
        "sessions": 25865,
        "newUsers": 17002,
        "avgDuration": 143,
        "bounceRate": 35
      },
      {
        "name": "History",
        "path": "/history/",
        "sessions": 23206,
        "newUsers": 12855,
        "avgDuration": 150,
        "bounceRate": 28
      },
      {
        "name": "Oceanography",
        "path": "/oceanography/",
        "sessions": 22410,
        "newUsers": 15667,
        "avgDuration": 147,
        "bounceRate": 40
      },
      {
        "name": "Anthropology",
        "path": "/anthropology/",
        "sessions": 19055,
        "newUsers": 14710,
        "avgDuration": 109,
        "bounceRate": 36
      }
    ],
    "deptTrend": {
      "labels": [
        "Jan",
        "Feb",
        "Mar",
        "Apr",
        "May",
        "Jun"
      ],
      "departments": {
        "Anthropology": [
          1547,
          5463,
          4377,
          2400,
          1729,
          3908
        ],
        "Atmospheric Sciences": [
          2952,
          9623,
          32935,
          4389,
          4693,
          2998
        ],
        "Biology": [
          14328,
          20498,
          22335,
          23154,
          18325,
          13186
        ],
        "Chemistry": [
          12223,
          26549,
          21466,
          19707,
          18357,
          14564
        ],
        "Communication & Journalism": [
          4641,
          5408,
          5914,
          7863,
          5257,
          3317
        ],
        "Economics": [
          12677,
          9120,
          11876,
          10933,
          8249,
          5564
        ],
        "English": [
          3467,
          3922,
          13509,
          10899,
          4451,
          6125
        ],
        "Geography": [
          7267,
          7009,
          10164,
          6088,
          4080,
          2643
        ],
        "Geology & Geophysics": [
          2706,
          6842,
          19118,
          10593,
          5748,
          2635
        ],
        "Global Languages & Cultures": [
          2575,
          15805,
          4554,
          5505,
          3202,
          2402
        ],
        "History": [
          1848,
          3412,
          6826,
          4838,
          4106,
          2044
        ],
        "Mathematics": [
          21325,
          28670,
          24123,
          33072,
          26689,
          19814
        ],
        "Oceanography": [
          2705,
          3261,
          6783,
          4398,
          2971,
          1817
        ],
        "Philosophy": [
          12015,
          4261,
          6490,
          5761,
          3057,
          1826
        ],
        "Physics & Astronomy": [
          11750,
          6257,
          5737,
          7966,
          5976,
          4174
        ],
        "Psychological & Brain Sciences": [
          12698,
          17466,
          18956,
          23515,
          16704,
          11867
        ],
        "Sociology": [
          2506,
          3708,
          9910,
          6733,
          3295,
          2022
        ],
        "Statistics": [
          11965,
          7661,
          8191,
          7863,
          6211,
          5087
        ]
      }
    }
  },
  "siteimprove": {
    "scope": "artsci.tamu.edu (Cascade sites)",
    "accessibilityScore": {
      "value": "83",
      "raw": 83
    },
    "accessibilityAA": {
      "value": "83",
      "raw": 83
    },
    "accessibilityTotal": {
      "value": "89",
      "raw": 89
    },
    "seoScore": {
      "value": "83",
      "raw": 83
    },
    "mobileScore": {
      "value": "59",
      "raw": 59
    },
    "qaScore": {
      "value": "59",
      "raw": 59
    },
    "dciTotal": {
      "value": "77",
      "raw": 77
    },
    "brokenLinks": {
      "value": "1529",
      "raw": 1529
    },
    "qualityIssues": {
      "value": "137",
      "raw": 137
    }
  },
  "freshdesk": {
    "ticketVolume": {
      "value": "300",
      "raw": 300
    },
    "resolutionRate": {
      "value": "92%",
      "raw": 92
    },
    "avgResponseTime": {
      "value": "7.0h",
      "raw": "7.0"
    },
    "csatScore": {
      "value": "N/A",
      "raw": "N/A"
    },
    "deptBreakdown": [
      {
        "name": "Other / Unclassified",
        "count": 178
      },
      {
        "name": "History",
        "count": 50
      },
      {
        "name": "Geography",
        "count": 14
      },
      {
        "name": "Geology & Geophysics",
        "count": 13
      },
      {
        "name": "Chemistry",
        "count": 8
      },
      {
        "name": "Communication & Journalism",
        "count": 7
      },
      {
        "name": "Biology",
        "count": 6
      },
      {
        "name": "English",
        "count": 6
      },
      {
        "name": "Atmospheric Sciences",
        "count": 5
      },
      {
        "name": "Oceanography",
        "count": 3
      }
    ],
    "ticketTrend": [
      {
        "label": "Mar 29",
        "count": 29
      },
      {
        "label": "Apr 5",
        "count": 15
      },
      {
        "label": "Apr 12",
        "count": 12
      },
      {
        "label": "Apr 19",
        "count": 23
      },
      {
        "label": "Apr 26",
        "count": 27
      },
      {
        "label": "May 3",
        "count": 18
      },
      {
        "label": "May 10",
        "count": 20
      },
      {
        "label": "May 17",
        "count": 44
      },
      {
        "label": "May 24",
        "count": 20
      },
      {
        "label": "May 31",
        "count": 8
      },
      {
        "label": "Jun 7",
        "count": 22
      },
      {
        "label": "Jun 14",
        "count": 16
      }
    ]
  },
  "clarity": {
    "status": "active",
    "hasData": true,
    "dataWindow": "Last 3 days (API limit)",
    "totalSessions": {
      "value": "5.8k",
      "raw": 5836
    },
    "uniqueUsers": {
      "value": "?",
      "raw": 0
    },
    "scrollDepth": {
      "value": "?",
      "raw": 0
    },
    "deadClicks": {
      "value": "2.8k",
      "raw": 2841
    },
    "deadClickRate": {
      "value": "49%",
      "raw": 49
    },
    "rageClicks": {
      "value": "?",
      "raw": 0
    },
    "recordings": {
      "value": "?",
      "raw": 0
    },
    "pageViews": {
      "value": "982",
      "raw": 982
    },
    "topPages": [],
    "rawData": [
      {
        "sessionsCount": "5",
        "sessionsWithMetricPercentage": 0,
        "sessionsWithoutMetricPercentage": 100,
        "pagesViews": "0",
        "subTotal": "0",
        "Browser": "Other",
        "Device": "Mobile"
      },
      {
        "sessionsCount": "2",
        "sessionsWithMetricPercentage": 0,
        "sessionsWithoutMetricPercentage": 100,
        "pagesViews": "0",
        "subTotal": "0",
        "Browser": "Chrome",
        "Device": "Mobile"
      },
      {
        "sessionsCount": "756",
        "sessionsWithMetricPercentage": 5.82,
        "sessionsWithoutMetricPercentage": 94.18,
        "pagesViews": "54",
        "subTotal": "113",
        "Browser": "ChromeMobile",
        "Device": "Mobile"
      }
    ]
  },
  "centersInventory": [
    {
      "name": "Race and Ethnic Studies Institute",
      "url": "https://liberalarts.tamu.edu/resi/",
      "platform": "WordPress",
      "monitored": false
    },
    {
      "name": "Glasscock Center for Humanities Research",
      "url": "https://liberalarts.tamu.edu/glasscock/",
      "platform": "WordPress",
      "monitored": false
    },
    {
      "name": "Center of Digital Humanities Research",
      "url": "https://liberalarts.tamu.edu/codhr/",
      "platform": "WordPress",
      "monitored": true
    },
    {
      "name": "Center for the Study of First Americans",
      "url": "https://liberalarts.tamu.edu/csfa/",
      "platform": "WordPress",
      "monitored": true
    },
    {
      "name": "Texas Research Data Center",
      "url": "https://liberalarts.tamu.edu/txrdc/",
      "platform": "WordPress",
      "monitored": false
    },
    {
      "name": "Berg-Hughes Center",
      "url": "https://berg-hughes.tamu.edu/",
      "platform": "Cascade",
      "monitored": true
    },
    {
      "name": "Ctr for Approximation & Mathematical Data",
      "url": "https://sites.google.com/tamu.edu/camda/",
      "platform": "Google Sites",
      "monitored": true
    },
    {
      "name": "Ctr for Atmospheric Chemistry & Environment",
      "url": "https://cace.tamu.edu/",
      "platform": "Cascade",
      "monitored": true
    },
    {
      "name": "Center for Biological Clocks Research",
      "url": "https://clocks.tamu.edu/",
      "platform": "WordPress",
      "monitored": false
    },
    {
      "name": "Ctr for Chemical Characterization & Analysis",
      "url": "https://sites.google.com/view/elemental-analysis-laboratory/",
      "platform": "Google Sites",
      "monitored": true
    },
    {
      "name": "Ctr for Electrochemical Systems & H Research",
      "url": "http://www.txpec.net/",
      "platform": "Unknown",
      "monitored": true
    },
    {
      "name": "Ctr for Maritime Archaeology & Conservation",
      "url": "https://nautarch.tamu.edu/",
      "platform": "WordPress",
      "monitored": false
    },
    {
      "name": "Ctr for Mathematics and Science Education",
      "url": "https://cmse.tamu.edu/",
      "platform": "WordPress",
      "monitored": false
    },
    {
      "name": "Center for Statistical Bioinformatics",
      "url": "https://statbio.stat.tamu.edu/",
      "platform": "WordPress",
      "monitored": true
    },
    {
      "name": "Ctr for Surface Science & Mechanochemistry",
      "url": "https://www.chem.tamu.edu/cmcc/",
      "platform": "HTML/CSS",
      "monitored": false
    },
    {
      "name": "Center for Tectonophysics",
      "url": "https://tectono.tamu.edu/",
      "platform": "Cascade",
      "monitored": true
    },
    {
      "name": "Center for Theoretical Physics",
      "url": "https://iqse.tamu.edu/ctp/",
      "platform": "WordPress",
      "monitored": false
    },
    {
      "name": "Cyclotron Institute",
      "url": "https://cyclotron.tamu.edu/",
      "platform": "WordPress",
      "monitored": false
    },
    {
      "name": "Geochemical & Environmental Research Group",
      "url": "https://gerg.tamu.edu/",
      "platform": "Cascade",
      "monitored": true
    },
    {
      "name": "Mitchell Institute for Physics & Astronomy",
      "url": "https://mitchell.tamu.edu/",
      "platform": "WordPress",
      "monitored": false
    },
    {
      "name": "Inst. for Applied Math & Computational Science",
      "url": "https://iamcs.tamu.edu/",
      "platform": "WordPress",
      "monitored": false
    },
    {
      "name": "Institute for Scientific Computation",
      "url": "https://isc.tamu.edu/",
      "platform": "HTML/CSS",
      "monitored": false
    },
    {
      "name": "Institute for Quantum Science and Engineering",
      "url": "https://iqse.tamu.edu/",
      "platform": "WordPress",
      "monitored": false
    },
    {
      "name": "Institute of Nautical Archaeology",
      "url": "https://nauticalarch.org/",
      "platform": "WordPress",
      "monitored": false
    },
    {
      "name": "Laboratory for Synthetic Biologic Interactions",
      "url": "https://lsbi.chem.tamu.edu/",
      "platform": "HTML/CSS",
      "monitored": false
    },
    {
      "name": "Nuclear Solutions Institute",
      "url": "https://nsi.tamu.edu/",
      "platform": "WordPress",
      "monitored": false
    },
    {
      "name": "Office of the Texas State Climatologist",
      "url": "https://climatexas.tamu.edu/",
      "platform": "Cascade",
      "monitored": true
    },
    {
      "name": "Public Policy Research Institute",
      "url": "https://ppri.tamu.edu/",
      "platform": "WordPress",
      "monitored": false
    },
    {
      "name": "Southern Regional Climate Center",
      "url": "https://www.srcc.tamu.edu/",
      "platform": "HTML/CSS",
      "monitored": false
    },
    {
      "name": "Texas Center for Extreme Weather",
      "url": "https://texasclimate.tamu.edu/",
      "platform": "Cascade",
      "monitored": true
    }
  ]
}