{
  "lastUpdated": "2026-06-07T12:14:29.912Z",
  "reportPeriod": {
    "days": 30,
    "startDate": "2026-05-08",
    "endDate": "2026-06-07",
    "startISO": "2026-05-08T12:14:21.633Z",
    "endISO": "2026-06-07T12:14:21.633Z",
    "label": "May 8, 2026 ? Jun 7, 2026"
  },
  "college": "College of Arts & Sciences",
  "domain": "artsci.tamu.edu",
  "ga4": {
    "sessions": {
      "value": "208.6k",
      "raw": 208589
    },
    "newUsers": {
      "value": "148.1k",
      "raw": 148062
    },
    "engagementRate": {
      "value": "34%",
      "raw": 34
    },
    "avgDuration": {
      "value": "2:37",
      "raw": 157
    },
    "pageViews": {
      "value": "323.7k",
      "raw": 323683
    },
    "bounceRate": {
      "value": "66%",
      "raw": 66
    },
    "admissionsVisits": {
      "value": "1.7k",
      "raw": 1709
    },
    "topPages": [
      {
        "path": "/",
        "views": 10104
      },
      {
        "path": "/geosonline/index.html",
        "views": 7597
      },
      {
        "path": "/english/index.html",
        "views": 5197
      },
      {
        "path": "/biology/index.html",
        "views": 4104
      },
      {
        "path": "/mathematics/index.html",
        "views": 2884
      }
    ],
    "monthlyTrend": {
      "buckets": [
        {
          "sessions": 42001,
          "newUsers": 27561,
          "bounceRate": 62
        },
        {
          "sessions": 34381,
          "newUsers": 23730,
          "bounceRate": 62
        },
        {
          "sessions": 33525,
          "newUsers": 23834,
          "bounceRate": 66
        },
        {
          "sessions": 38900,
          "newUsers": 28326,
          "bounceRate": 68
        },
        {
          "sessions": 33182,
          "newUsers": 24338,
          "bounceRate": 65
        },
        {
          "sessions": 31366,
          "newUsers": 22168,
          "bounceRate": 65
        },
        {
          "sessions": 28377,
          "newUsers": 20896,
          "bounceRate": 69
        }
      ],
      "labels": [
        "5/4",
        "5/9",
        "5/14",
        "5/19",
        "5/24",
        "5/29",
        "6/3"
      ]
    },
    "deptBreakdown": [
      {
        "name": "Mathematics",
        "path": "/mathematics/",
        "sessions": 21422,
        "newUsers": 13896,
        "avgDuration": 130,
        "bounceRate": 34
      },
      {
        "name": "Biology",
        "path": "/biology/",
        "sessions": 16962,
        "newUsers": 9268,
        "avgDuration": 183,
        "bounceRate": 28
      },
      {
        "name": "Chemistry",
        "path": "/chemistry/",
        "sessions": 14934,
        "newUsers": 8107,
        "avgDuration": 151,
        "bounceRate": 32
      },
      {
        "name": "Psychological & Brain Sciences",
        "path": "/psychological-brain-sciences/",
        "sessions": 13673,
        "newUsers": 7565,
        "avgDuration": 197,
        "bounceRate": 28
      },
      {
        "name": "English",
        "path": "/english/",
        "sessions": 6440,
        "newUsers": 5597,
        "avgDuration": 110,
        "bounceRate": 31
      },
      {
        "name": "Economics",
        "path": "/economics/",
        "sessions": 6140,
        "newUsers": 3278,
        "avgDuration": 148,
        "bounceRate": 24
      },
      {
        "name": "Statistics",
        "path": "/statistics/",
        "sessions": 5639,
        "newUsers": 3362,
        "avgDuration": 163,
        "bounceRate": 31
      },
      {
        "name": "Physics & Astronomy",
        "path": "/physics-astronomy/",
        "sessions": 4671,
        "newUsers": 3158,
        "avgDuration": 109,
        "bounceRate": 34
      },
      {
        "name": "Communication & Journalism",
        "path": "/comm-journalism/",
        "sessions": 3982,
        "newUsers": 2506,
        "avgDuration": 165,
        "bounceRate": 26
      },
      {
        "name": "Atmospheric Sciences",
        "path": "/atmos-science/",
        "sessions": 3258,
        "newUsers": 2190,
        "avgDuration": 137,
        "bounceRate": 40
      },
      {
        "name": "Geology & Geophysics",
        "path": "/geology-geophysics/",
        "sessions": 3078,
        "newUsers": 1955,
        "avgDuration": 132,
        "bounceRate": 36
      },
      {
        "name": "Geography",
        "path": "/geography/",
        "sessions": 2820,
        "newUsers": 1638,
        "avgDuration": 208,
        "bounceRate": 33
      },
      {
        "name": "Global Languages & Cultures",
        "path": "/global-lang-cultures/",
        "sessions": 2764,
        "newUsers": 1613,
        "avgDuration": 152,
        "bounceRate": 24
      },
      {
        "name": "History",
        "path": "/history/",
        "sessions": 2452,
        "newUsers": 1464,
        "avgDuration": 130,
        "bounceRate": 26
      },
      {
        "name": "Philosophy",
        "path": "/philosophy/",
        "sessions": 2109,
        "newUsers": 1310,
        "avgDuration": 104,
        "bounceRate": 37
      },
      {
        "name": "Sociology",
        "path": "/sociology/",
        "sessions": 2037,
        "newUsers": 938,
        "avgDuration": 116,
        "bounceRate": 36
      },
      {
        "name": "Oceanography",
        "path": "/oceanography/",
        "sessions": 1834,
        "newUsers": 1235,
        "avgDuration": 150,
        "bounceRate": 37
      },
      {
        "name": "Anthropology",
        "path": "/anthropology/",
        "sessions": 1289,
        "newUsers": 917,
        "avgDuration": 109,
        "bounceRate": 31
      }
    ],
    "deptTrend": {
      "labels": [
        "Jun"
      ],
      "departments": {
        "Anthropology": [
          1304
        ],
        "Atmospheric Sciences": [
          3133
        ],
        "Biology": [
          16439
        ],
        "Chemistry": [
          14614
        ],
        "Communication & Journalism": [
          3807
        ],
        "Economics": [
          5911
        ],
        "English": [
          6299
        ],
        "Geography": [
          2816
        ],
        "Geology & Geophysics": [
          2752
        ],
        "Global Languages & Cultures": [
          2638
        ],
        "History": [
          2332
        ],
        "Mathematics": [
          20713
        ],
        "Oceanography": [
          1762
        ],
        "Philosophy": [
          2016
        ],
        "Physics & Astronomy": [
          4369
        ],
        "Psychological & Brain Sciences": [
          13112
        ],
        "Sociology": [
          1951
        ],
        "Statistics": [
          5570
        ]
      }
    }
  },
  "siteimprove": {
    "scope": "artsci.tamu.edu (Cascade sites)",
    "accessibilityScore": {
      "value": "83",
      "raw": 83
    },
    "accessibilityAA": {
      "value": "83",
      "raw": 83
    },
    "accessibilityTotal": {
      "value": "89",
      "raw": 89
    },
    "seoScore": {
      "value": "83",
      "raw": 83
    },
    "mobileScore": {
      "value": "58",
      "raw": 58
    },
    "qaScore": {
      "value": "61",
      "raw": 61
    },
    "dciTotal": {
      "value": "78",
      "raw": 78
    },
    "brokenLinks": {
      "value": "1540",
      "raw": 1540
    },
    "qualityIssues": {
      "value": "139",
      "raw": 139
    }
  },
  "freshdesk": {
    "ticketVolume": {
      "value": "126",
      "raw": 126
    },
    "resolutionRate": {
      "value": "89%",
      "raw": 89
    },
    "avgResponseTime": {
      "value": "10.8h",
      "raw": "10.8"
    },
    "csatScore": {
      "value": "N/A",
      "raw": "N/A"
    },
    "deptBreakdown": [
      {
        "name": "Other / Unclassified",
        "count": 64
      },
      {
        "name": "History",
        "count": 36
      },
      {
        "name": "English",
        "count": 6
      },
      {
        "name": "Communication & Journalism",
        "count": 4
      },
      {
        "name": "Geography",
        "count": 3
      },
      {
        "name": "Economics",
        "count": 3
      },
      {
        "name": "Oceanography",
        "count": 2
      },
      {
        "name": "Geology & Geophysics",
        "count": 2
      },
      {
        "name": "Atmospheric Sciences",
        "count": 2
      },
      {
        "name": "Chemistry",
        "count": 2
      }
    ],
    "ticketTrend": [
      {
        "label": "May 10",
        "count": 19
      },
      {
        "label": "May 17",
        "count": 44
      },
      {
        "label": "May 24",
        "count": 20
      },
      {
        "label": "May 31",
        "count": 8
      },
      {
        "label": "Jun 7",
        "count": 22
      }
    ]
  },
  "clarity": {
    "status": "active",
    "hasData": true,
    "dataWindow": "Last 3 days (API limit)",
    "totalSessions": {
      "value": "10.6k",
      "raw": 10633
    },
    "uniqueUsers": {
      "value": "?",
      "raw": 0
    },
    "scrollDepth": {
      "value": "?",
      "raw": 0
    },
    "deadClicks": {
      "value": "2.2k",
      "raw": 2226
    },
    "deadClickRate": {
      "value": "21%",
      "raw": 21
    },
    "rageClicks": {
      "value": "?",
      "raw": 0
    },
    "recordings": {
      "value": "?",
      "raw": 0
    },
    "pageViews": {
      "value": "871",
      "raw": 871
    },
    "topPages": [],
    "rawData": [
      {
        "sessionsCount": "1",
        "sessionsWithMetricPercentage": 0,
        "sessionsWithoutMetricPercentage": 100,
        "pagesViews": "0",
        "subTotal": "0",
        "Browser": "Other",
        "Device": "Mobile"
      },
      {
        "sessionsCount": "495",
        "sessionsWithMetricPercentage": 6.87,
        "sessionsWithoutMetricPercentage": 93.13,
        "pagesViews": "36",
        "subTotal": "57",
        "Browser": "ChromeMobile",
        "Device": "Mobile"
      },
      {
        "sessionsCount": "7",
        "sessionsWithMetricPercentage": 0,
        "sessionsWithoutMetricPercentage": 100,
        "pagesViews": "0",
        "subTotal": "0",
        "Browser": "EdgeMobile",
        "Device": "Mobile"
      }
    ]
  },
  "centersInventory": [
    {
      "name": "Race and Ethnic Studies Institute",
      "url": "https://liberalarts.tamu.edu/resi/",
      "platform": "WordPress",
      "monitored": false
    },
    {
      "name": "Glasscock Center for Humanities Research",
      "url": "https://liberalarts.tamu.edu/glasscock/",
      "platform": "WordPress",
      "monitored": false
    },
    {
      "name": "Center of Digital Humanities Research",
      "url": "https://liberalarts.tamu.edu/codhr/",
      "platform": "WordPress",
      "monitored": true
    },
    {
      "name": "Center for the Study of First Americans",
      "url": "https://liberalarts.tamu.edu/csfa/",
      "platform": "WordPress",
      "monitored": true
    },
    {
      "name": "Texas Research Data Center",
      "url": "https://liberalarts.tamu.edu/txrdc/",
      "platform": "WordPress",
      "monitored": false
    },
    {
      "name": "Berg-Hughes Center",
      "url": "https://berg-hughes.tamu.edu/",
      "platform": "Cascade",
      "monitored": true
    },
    {
      "name": "Ctr for Approximation & Mathematical Data",
      "url": "https://sites.google.com/tamu.edu/camda/",
      "platform": "Google Sites",
      "monitored": true
    },
    {
      "name": "Ctr for Atmospheric Chemistry & Environment",
      "url": "https://cace.tamu.edu/",
      "platform": "Cascade",
      "monitored": true
    },
    {
      "name": "Center for Biological Clocks Research",
      "url": "https://clocks.tamu.edu/",
      "platform": "WordPress",
      "monitored": false
    },
    {
      "name": "Ctr for Chemical Characterization & Analysis",
      "url": "https://sites.google.com/view/elemental-analysis-laboratory/",
      "platform": "Google Sites",
      "monitored": true
    },
    {
      "name": "Ctr for Electrochemical Systems & H Research",
      "url": "http://www.txpec.net/",
      "platform": "Unknown",
      "monitored": true
    },
    {
      "name": "Ctr for Maritime Archaeology & Conservation",
      "url": "https://nautarch.tamu.edu/",
      "platform": "WordPress",
      "monitored": false
    },
    {
      "name": "Ctr for Mathematics and Science Education",
      "url": "https://cmse.tamu.edu/",
      "platform": "WordPress",
      "monitored": false
    },
    {
      "name": "Center for Statistical Bioinformatics",
      "url": "https://statbio.stat.tamu.edu/",
      "platform": "WordPress",
      "monitored": true
    },
    {
      "name": "Ctr for Surface Science & Mechanochemistry",
      "url": "https://www.chem.tamu.edu/cmcc/",
      "platform": "HTML/CSS",
      "monitored": false
    },
    {
      "name": "Center for Tectonophysics",
      "url": "https://tectono.tamu.edu/",
      "platform": "Cascade",
      "monitored": true
    },
    {
      "name": "Center for Theoretical Physics",
      "url": "https://iqse.tamu.edu/ctp/",
      "platform": "WordPress",
      "monitored": false
    },
    {
      "name": "Cyclotron Institute",
      "url": "https://cyclotron.tamu.edu/",
      "platform": "WordPress",
      "monitored": false
    },
    {
      "name": "Geochemical & Environmental Research Group",
      "url": "https://gerg.tamu.edu/",
      "platform": "Cascade",
      "monitored": true
    },
    {
      "name": "Mitchell Institute for Physics & Astronomy",
      "url": "https://mitchell.tamu.edu/",
      "platform": "WordPress",
      "monitored": false
    },
    {
      "name": "Inst. for Applied Math & Computational Science",
      "url": "https://iamcs.tamu.edu/",
      "platform": "WordPress",
      "monitored": false
    },
    {
      "name": "Institute for Scientific Computation",
      "url": "https://isc.tamu.edu/",
      "platform": "HTML/CSS",
      "monitored": false
    },
    {
      "name": "Institute for Quantum Science and Engineering",
      "url": "https://iqse.tamu.edu/",
      "platform": "WordPress",
      "monitored": false
    },
    {
      "name": "Institute of Nautical Archaeology",
      "url": "https://nauticalarch.org/",
      "platform": "WordPress",
      "monitored": false
    },
    {
      "name": "Laboratory for Synthetic Biologic Interactions",
      "url": "https://lsbi.chem.tamu.edu/",
      "platform": "HTML/CSS",
      "monitored": false
    },
    {
      "name": "Nuclear Solutions Institute",
      "url": "https://nsi.tamu.edu/",
      "platform": "WordPress",
      "monitored": false
    },
    {
      "name": "Office of the Texas State Climatologist",
      "url": "https://climatexas.tamu.edu/",
      "platform": "Cascade",
      "monitored": true
    },
    {
      "name": "Public Policy Research Institute",
      "url": "https://ppri.tamu.edu/",
      "platform": "WordPress",
      "monitored": false
    },
    {
      "name": "Southern Regional Climate Center",
      "url": "https://www.srcc.tamu.edu/",
      "platform": "HTML/CSS",
      "monitored": false
    },
    {
      "name": "Texas Center for Extreme Weather",
      "url": "https://texasclimate.tamu.edu/",
      "platform": "Cascade",
      "monitored": true
    }
  ]
}